{
  "diff_id": "british_gp_20260705T000000_0000_7b3523f57969",
  "generated_at": "2026-07-06T06:38:39+00:00",
  "base_run_id": "british_gp_20260705T000000_0000_20260706T060527_0000_a01da2eb35",
  "candidate_run_id": "british_gp_20260705T000000_0000_20260706T063838_0000_22806fdba8",
  "event_id": "british_gp",
  "match_warnings": [],
  "input_changed": true,
  "evidence_changed": false,
  "probability_changed": true,
  "information_intake_changed": true,
  "driver_deltas": [
    {
      "driver_id": "albon",
      "base_win": 0.0,
      "candidate_win": 0.0,
      "win_delta": 0.0,
      "base_podium": 0.0,
      "candidate_podium": 0.0,
      "podium_delta": 0.0,
      "base_expected_points": 0.43,
      "candidate_expected_points": 0.4317,
      "expected_points_delta": 0.0017,
      "base_average_finish": 14.2217,
      "candidate_average_finish": 14.2208,
      "average_finish_delta": -0.0008,
      "base_expected_rank": 14,
      "candidate_expected_rank": 14,
      "expected_rank_delta": 0
    },
    {
      "driver_id": "alonso",
      "base_win": 0.0,
      "candidate_win": 0.0,
      "win_delta": 0.0,
      "base_podium": 0.0,
      "candidate_podium": 0.0,
      "podium_delta": 0.0,
      "base_expected_points": 0.2333,
      "candidate_expected_points": 0.2333,
      "expected_points_delta": 0.0,
      "base_average_finish": 15.4283,
      "candidate_average_finish": 15.4283,
      "average_finish_delta": 0.0,
      "base_expected_rank": 15,
      "candidate_expected_rank": 15,
      "expected_rank_delta": 0
    },
    {
      "driver_id": "antonelli",
      "base_win": 0.453333,
      "candidate_win": 0.450833,
      "win_delta": -0.0025,
      "base_podium": 0.900833,
      "candidate_podium": 0.898333,
      "podium_delta": -0.0025,
      "base_expected_points": 19.7358,
      "candidate_expected_points": 19.6817,
      "expected_points_delta": -0.0542,
      "base_average_finish": 2.5908,
      "candidate_average_finish": 2.6058,
      "average_finish_delta": 0.015,
      "base_expected_rank": 2,
      "candidate_expected_rank": 2,
      "expected_rank_delta": 0
    },
    {
      "driver_id": "bearman",
      "base_win": 0.0,
      "candidate_win": 0.0,
      "win_delta": 0.0,
      "base_podium": 0.0,
      "candidate_podium": 0.0,
      "podium_delta": 0.0,
      "base_expected_points": 0.2083,
      "candidate_expected_points": 0.2083,
      "expected_points_delta": 0.0,
      "base_average_finish": 15.6933,
      "candidate_average_finish": 15.6933,
      "average_finish_delta": 0.0,
      "base_expected_rank": 17,
      "candidate_expected_rank": 17,
      "expected_rank_delta": 0
    },
    {
      "driver_id": "bortoleto",
      "base_win": 0.0,
      "candidate_win": 0.0,
      "win_delta": 0.0,
      "base_podium": 0.0,
      "candidate_podium": 0.0,
      "podium_delta": 0.0,
      "base_expected_points": 0.0942,
      "candidate_expected_points": 0.0942,
      "expected_points_delta": 0.0,
      "base_average_finish": 16.7183,
      "candidate_average_finish": 16.7183,
      "average_finish_delta": 0.0,
      "base_expected_rank": 20,
      "candidate_expected_rank": 20,
      "expected_rank_delta": 0
    },
    {
      "driver_id": "bottas",
      "base_win": 0.0,
      "candidate_win": 0.0,
      "win_delta": 0.0,
      "base_podium": 0.0,
      "candidate_podium": 0.0,
      "podium_delta": 0.0,
      "base_expected_points": 0.0542,
      "candidate_expected_points": 0.0542,
      "expected_points_delta": 0.0,
      "base_average_finish": 17.7592,
      "candidate_average_finish": 17.7592,
      "average_finish_delta": 0.0,
      "base_expected_rank": 21,
      "candidate_expected_rank": 21,
      "expected_rank_delta": 0
    },
    {
      "driver_id": "colapinto",
      "base_win": 0.0,
      "candidate_win": 0.0,
      "win_delta": 0.0,
      "base_podium": 0.0,
      "candidate_podium": 0.0,
      "podium_delta": 0.0,
      "base_expected_points": 0.7333,
      "candidate_expected_points": 0.7358,
      "expected_points_delta": 0.0025,
      "base_average_finish": 13.0633,
      "candidate_average_finish": 13.0617,
      "average_finish_delta": -0.0017,
      "base_expected_rank": 10,
      "candidate_expected_rank": 10,
      "expected_rank_delta": 0
    },
    {
      "driver_id": "gasly",
      "base_win": 0.0,
      "candidate_win": 0.0,
      "win_delta": 0.0,
      "base_podium": 0.0,
      "candidate_podium": 0.0,
      "podium_delta": 0.0,
      "base_expected_points": 1.1642,
      "candidate_expected_points": 1.1633,
      "expected_points_delta": -0.0008,
      "base_average_finish": 12.0158,
      "candidate_average_finish": 12.0167,
      "average_finish_delta": 0.0008,
      "base_expected_rank": 9,
      "candidate_expected_rank": 9,
      "expected_rank_delta": 0
    },
    {
      "driver_id": "hadjar",
      "base_win": 0.001667,
      "candidate_win": 0.001667,
      "win_delta": 0.0,
      "base_podium": 0.058333,
      "candidate_podium": 0.055833,
      "podium_delta": -0.0025,
      "base_expected_points": 6.6275,
      "candidate_expected_points": 6.5583,
      "expected_points_delta": -0.0692,
      "base_average_finish": 7.7142,
      "candidate_average_finish": 7.75,
      "average_finish_delta": 0.0358,
      "base_expected_rank": 8,
      "candidate_expected_rank": 8,
      "expected_rank_delta": 0
    },
    {
      "driver_id": "hamilton",
      "base_win": 0.04,
      "candidate_win": 0.043333,
      "win_delta": 0.003333,
      "base_podium": 0.4425,
      "candidate_podium": 0.4625,
      "podium_delta": 0.02,
      "base_expected_points": 12.2358,
      "candidate_expected_points": 12.4658,
      "expected_points_delta": 0.23,
      "base_average_finish": 4.7975,
      "candidate_average_finish": 4.71,
      "average_finish_delta": -0.0875,
      "base_expected_rank": 3,
      "candidate_expected_rank": 3,
      "expected_rank_delta": 0
    },
    {
      "driver_id": "hulkenberg",
      "base_win": 0.0,
      "candidate_win": 0.0,
      "win_delta": 0.0,
      "base_podium": 0.0,
      "candidate_podium": 0.0,
      "podium_delta": 0.0,
      "base_expected_points": 0.1017,
      "candidate_expected_points": 0.1017,
      "expected_points_delta": 0.0,
      "base_average_finish": 16.5775,
      "candidate_average_finish": 16.5775,
      "average_finish_delta": 0.0,
      "base_expected_rank": 19,
      "candidate_expected_rank": 19,
      "expected_rank_delta": 0
    },
    {
      "driver_id": "lawson",
      "base_win": 0.0,
      "candidate_win": 0.0,
      "win_delta": 0.0,
      "base_podium": 0.0,
      "candidate_podium": 0.0,
      "podium_delta": 0.0,
      "base_expected_points": 0.5517,
      "candidate_expected_points": 0.5525,
      "expected_points_delta": 0.0008,
      "base_average_finish": 13.6283,
      "candidate_average_finish": 13.6275,
      "average_finish_delta": -0.0008,
      "base_expected_rank": 13,
      "candidate_expected_rank": 13,
      "expected_rank_delta": 0
    },
    {
      "driver_id": "leclerc",
      "base_win": 0.016667,
      "candidate_win": 0.0175,
      "win_delta": 0.000833,
      "base_podium": 0.2175,
      "candidate_podium": 0.2275,
      "podium_delta": 0.01,
      "base_expected_points": 9.7517,
      "candidate_expected_points": 9.9183,
      "expected_points_delta": 0.1667,
      "base_average_finish": 6.0258,
      "candidate_average_finish": 5.9517,
      "average_finish_delta": -0.0742,
      "base_expected_rank": 5,
      "candidate_expected_rank": 5,
      "expected_rank_delta": 0
    },
    {
      "driver_id": "lindblad",
      "base_win": 0.0,
      "candidate_win": 0.0,
      "win_delta": 0.0,
      "base_podium": 0.0,
      "candidate_podium": 0.0,
      "podium_delta": 0.0,
      "base_expected_points": 0.7075,
      "candidate_expected_points": 0.7058,
      "expected_points_delta": -0.0017,
      "base_average_finish": 13.1317,
      "candidate_average_finish": 13.1333,
      "average_finish_delta": 0.0017,
      "base_expected_rank": 11,
      "candidate_expected_rank": 11,
      "expected_rank_delta": 0
    },
    {
      "driver_id": "norris",
      "base_win": 0.01,
      "candidate_win": 0.01,
      "win_delta": 0.0,
      "base_podium": 0.1925,
      "candidate_podium": 0.183333,
      "podium_delta": -0.009167,
      "base_expected_points": 9.6333,
      "candidate_expected_points": 9.5808,
      "expected_points_delta": -0.0525,
      "base_average_finish": 5.7583,
      "candidate_average_finish": 5.78,
      "average_finish_delta": 0.0217,
      "base_expected_rank": 4,
      "candidate_expected_rank": 4,
      "expected_rank_delta": 0
    },
    {
      "driver_id": "ocon",
      "base_win": 0.0,
      "candidate_win": 0.0,
      "win_delta": 0.0,
      "base_podium": 0.0,
      "candidate_podium": 0.0,
      "podium_delta": 0.0,
      "base_expected_points": 0.1842,
      "candidate_expected_points": 0.1842,
      "expected_points_delta": 0.0,
      "base_average_finish": 15.6375,
      "candidate_average_finish": 15.6367,
      "average_finish_delta": -0.0008,
      "base_expected_rank": 16,
      "candidate_expected_rank": 16,
      "expected_rank_delta": 0
    },
    {
      "driver_id": "perez",
      "base_win": 0.0,
      "candidate_win": 0.0,
      "win_delta": 0.0,
      "base_podium": 0.0,
      "candidate_podium": 0.0,
      "podium_delta": 0.0,
      "base_expected_points": 0.0392,
      "candidate_expected_points": 0.0392,
      "expected_points_delta": 0.0,
      "base_average_finish": 18.0258,
      "candidate_average_finish": 18.0258,
      "average_finish_delta": 0.0,
      "base_expected_rank": 22,
      "candidate_expected_rank": 22,
      "expected_rank_delta": 0
    },
    {
      "driver_id": "piastri",
      "base_win": 0.008333,
      "candidate_win": 0.008333,
      "win_delta": 0.0,
      "base_podium": 0.145833,
      "candidate_podium": 0.143333,
      "podium_delta": -0.0025,
      "base_expected_points": 8.995,
      "candidate_expected_points": 8.975,
      "expected_points_delta": -0.02,
      "base_average_finish": 6.1225,
      "candidate_average_finish": 6.1317,
      "average_finish_delta": 0.0092,
      "base_expected_rank": 6,
      "candidate_expected_rank": 6,
      "expected_rank_delta": 0
    },
    {
      "driver_id": "russell",
      "base_win": 0.464167,
      "candidate_win": 0.4625,
      "win_delta": -0.001667,
      "base_podium": 0.9075,
      "candidate_podium": 0.904167,
      "podium_delta": -0.003333,
      "base_expected_points": 19.905,
      "candidate_expected_points": 19.8342,
      "expected_points_delta": -0.0708,
      "base_average_finish": 2.4842,
      "candidate_average_finish": 2.5058,
      "average_finish_delta": 0.0217,
      "base_expected_rank": 1,
      "candidate_expected_rank": 1,
      "expected_rank_delta": 0
    },
    {
      "driver_id": "sainz",
      "base_win": 0.0,
      "candidate_win": 0.0,
      "win_delta": 0.0,
      "base_podium": 0.0,
      "candidate_podium": 0.0,
      "podium_delta": 0.0,
      "base_expected_points": 0.6225,
      "candidate_expected_points": 0.62,
      "expected_points_delta": -0.0025,
      "base_average_finish": 13.4358,
      "candidate_average_finish": 13.4375,
      "average_finish_delta": 0.0017,
      "base_expected_rank": 12,
      "candidate_expected_rank": 12,
      "expected_rank_delta": 0
    },
    {
      "driver_id": "stroll",
      "base_win": 0.0,
      "candidate_win": 0.0,
      "win_delta": 0.0,
      "base_podium": 0.0,
      "candidate_podium": 0.0,
      "podium_delta": 0.0,
      "base_expected_points": 0.1717,
      "candidate_expected_points": 0.1717,
      "expected_points_delta": 0.0,
      "base_average_finish": 15.8,
      "candidate_average_finish": 15.7992,
      "average_finish_delta": -0.0008,
      "base_expected_rank": 18,
      "candidate_expected_rank": 18,
      "expected_rank_delta": 0
    },
    {
      "driver_id": "verstappen",
      "base_win": 0.005833,
      "candidate_win": 0.005833,
      "win_delta": 0.0,
      "base_podium": 0.135,
      "candidate_podium": 0.125,
      "podium_delta": -0.01,
      "base_expected_points": 8.82,
      "candidate_expected_points": 8.69,
      "expected_points_delta": -0.13,
      "base_average_finish": 6.37,
      "candidate_average_finish": 6.4292,
      "average_finish_delta": 0.0592,
      "base_expected_rank": 7,
      "candidate_expected_rank": 7,
      "expected_rank_delta": 0
    }
  ],
  "largest_changes": [
    {
      "driver_id": "hamilton",
      "base_win": 0.04,
      "candidate_win": 0.043333,
      "win_delta": 0.003333,
      "base_podium": 0.4425,
      "candidate_podium": 0.4625,
      "podium_delta": 0.02,
      "base_expected_points": 12.2358,
      "candidate_expected_points": 12.4658,
      "expected_points_delta": 0.23,
      "base_average_finish": 4.7975,
      "candidate_average_finish": 4.71,
      "average_finish_delta": -0.0875,
      "base_expected_rank": 3,
      "candidate_expected_rank": 3,
      "expected_rank_delta": 0
    },
    {
      "driver_id": "antonelli",
      "base_win": 0.453333,
      "candidate_win": 0.450833,
      "win_delta": -0.0025,
      "base_podium": 0.900833,
      "candidate_podium": 0.898333,
      "podium_delta": -0.0025,
      "base_expected_points": 19.7358,
      "candidate_expected_points": 19.6817,
      "expected_points_delta": -0.0542,
      "base_average_finish": 2.5908,
      "candidate_average_finish": 2.6058,
      "average_finish_delta": 0.015,
      "base_expected_rank": 2,
      "candidate_expected_rank": 2,
      "expected_rank_delta": 0
    },
    {
      "driver_id": "russell",
      "base_win": 0.464167,
      "candidate_win": 0.4625,
      "win_delta": -0.001667,
      "base_podium": 0.9075,
      "candidate_podium": 0.904167,
      "podium_delta": -0.003333,
      "base_expected_points": 19.905,
      "candidate_expected_points": 19.8342,
      "expected_points_delta": -0.0708,
      "base_average_finish": 2.4842,
      "candidate_average_finish": 2.5058,
      "average_finish_delta": 0.0217,
      "base_expected_rank": 1,
      "candidate_expected_rank": 1,
      "expected_rank_delta": 0
    },
    {
      "driver_id": "leclerc",
      "base_win": 0.016667,
      "candidate_win": 0.0175,
      "win_delta": 0.000833,
      "base_podium": 0.2175,
      "candidate_podium": 0.2275,
      "podium_delta": 0.01,
      "base_expected_points": 9.7517,
      "candidate_expected_points": 9.9183,
      "expected_points_delta": 0.1667,
      "base_average_finish": 6.0258,
      "candidate_average_finish": 5.9517,
      "average_finish_delta": -0.0742,
      "base_expected_rank": 5,
      "candidate_expected_rank": 5,
      "expected_rank_delta": 0
    },
    {
      "driver_id": "verstappen",
      "base_win": 0.005833,
      "candidate_win": 0.005833,
      "win_delta": 0.0,
      "base_podium": 0.135,
      "candidate_podium": 0.125,
      "podium_delta": -0.01,
      "base_expected_points": 8.82,
      "candidate_expected_points": 8.69,
      "expected_points_delta": -0.13,
      "base_average_finish": 6.37,
      "candidate_average_finish": 6.4292,
      "average_finish_delta": 0.0592,
      "base_expected_rank": 7,
      "candidate_expected_rank": 7,
      "expected_rank_delta": 0
    },
    {
      "driver_id": "hadjar",
      "base_win": 0.001667,
      "candidate_win": 0.001667,
      "win_delta": 0.0,
      "base_podium": 0.058333,
      "candidate_podium": 0.055833,
      "podium_delta": -0.0025,
      "base_expected_points": 6.6275,
      "candidate_expected_points": 6.5583,
      "expected_points_delta": -0.0692,
      "base_average_finish": 7.7142,
      "candidate_average_finish": 7.75,
      "average_finish_delta": 0.0358,
      "base_expected_rank": 8,
      "candidate_expected_rank": 8,
      "expected_rank_delta": 0
    },
    {
      "driver_id": "norris",
      "base_win": 0.01,
      "candidate_win": 0.01,
      "win_delta": 0.0,
      "base_podium": 0.1925,
      "candidate_podium": 0.183333,
      "podium_delta": -0.009167,
      "base_expected_points": 9.6333,
      "candidate_expected_points": 9.5808,
      "expected_points_delta": -0.0525,
      "base_average_finish": 5.7583,
      "candidate_average_finish": 5.78,
      "average_finish_delta": 0.0217,
      "base_expected_rank": 4,
      "candidate_expected_rank": 4,
      "expected_rank_delta": 0
    },
    {
      "driver_id": "piastri",
      "base_win": 0.008333,
      "candidate_win": 0.008333,
      "win_delta": 0.0,
      "base_podium": 0.145833,
      "candidate_podium": 0.143333,
      "podium_delta": -0.0025,
      "base_expected_points": 8.995,
      "candidate_expected_points": 8.975,
      "expected_points_delta": -0.02,
      "base_average_finish": 6.1225,
      "candidate_average_finish": 6.1317,
      "average_finish_delta": 0.0092,
      "base_expected_rank": 6,
      "candidate_expected_rank": 6,
      "expected_rank_delta": 0
    },
    {
      "driver_id": "colapinto",
      "base_win": 0.0,
      "candidate_win": 0.0,
      "win_delta": 0.0,
      "base_podium": 0.0,
      "candidate_podium": 0.0,
      "podium_delta": 0.0,
      "base_expected_points": 0.7333,
      "candidate_expected_points": 0.7358,
      "expected_points_delta": 0.0025,
      "base_average_finish": 13.0633,
      "candidate_average_finish": 13.0617,
      "average_finish_delta": -0.0017,
      "base_expected_rank": 10,
      "candidate_expected_rank": 10,
      "expected_rank_delta": 0
    },
    {
      "driver_id": "sainz",
      "base_win": 0.0,
      "candidate_win": 0.0,
      "win_delta": 0.0,
      "base_podium": 0.0,
      "candidate_podium": 0.0,
      "podium_delta": 0.0,
      "base_expected_points": 0.6225,
      "candidate_expected_points": 0.62,
      "expected_points_delta": -0.0025,
      "base_average_finish": 13.4358,
      "candidate_average_finish": 13.4375,
      "average_finish_delta": 0.0017,
      "base_expected_rank": 12,
      "candidate_expected_rank": 12,
      "expected_rank_delta": 0
    }
  ],
  "summary": {
    "driver_count": 22,
    "changed_driver_count": 14,
    "material_driver_change_count": 3,
    "max_abs_win_delta": 0.003333,
    "max_abs_expected_points_delta": 0.23,
    "rank_change_count": 0
  }
}