{
  "year": 2026,
  "as_of": "2026-07-01T00:00:00+00:00",
  "generated_at": "2026-07-05T11:15:35+00:00",
  "status": "diagnostic_only",
  "formal_edge_ready": false,
  "formal_backtest_ready": false,
  "formal_probability_claim_ready": false,
  "replay_scope": {
    "calendar_events": 24,
    "cancelled_events": 2,
    "due_events": 8,
    "replayed_events": 8,
    "result_available_events": 8,
    "missing_due_events": 0
  },
  "diagnostic_metrics": {
    "diagnostic_scored_events": 8,
    "top_pick_hits": 5,
    "top_pick_misses": 3,
    "top_pick_hit_rate": 0.625,
    "median_actual_winner_rank": 1,
    "mean_abs_rank_error": 5.1932,
    "mean_abs_points_error": 3.1375,
    "mean_podium_overlap_rate": 0.5417,
    "mean_points_overlap_rate": 0.6125,
    "events_with_evidence_impact": 8,
    "events_with_evidence_quality": 8,
    "events_with_weak_evidence_quality": 3,
    "events_with_strong_evidence_quality": 0,
    "max_evidence_win_delta": 0.0125,
    "input_source_breakdown": {
      "seed": {
        "events": 3,
        "hits": 2,
        "hit_rate": 0.6667
      },
      "openf1_calendar_generated": {
        "events": 5,
        "hits": 3,
        "hit_rate": 0.6
      }
    },
    "input_quality_breakdown": {
      "seed_with_fastf1_result": {
        "events": 3,
        "hits": 2,
        "hit_rate": 0.6667
      },
      "generated_verified": {
        "events": 5,
        "hits": 3,
        "hit_rate": 0.6
      }
    },
    "events_with_evidence": 8,
    "events_with_source_snapshots": 8,
    "events_with_retrospective_source_snapshots": 3,
    "events_with_archive_backed_source_snapshots": 5,
    "events_with_market_snapshots": 2,
    "events_with_market_snapshots_after_cutoff": 2,
    "events_needing_codex_research": 0
  },
  "readiness_summary": {
    "status": "inputs_required",
    "formal_backtest_ready": false,
    "blocking_action_count": 9,
    "warning_action_count": 5,
    "action_category_counts": {
      "model_calibration_review": 3,
      "after_cutoff_market_replacement": 2,
      "market_snapshot_required": 6,
      "source_archive_required": 3
    },
    "workstream_count": 4
  },
  "calibration_summary": {
    "status": "diagnostic_only",
    "formal_probability_claim_ready": false,
    "scored_events": 8,
    "market_scored_events": 1,
    "summary": {
      "top_pick_hits": 5,
      "top_pick_hit_rate": 0.625,
      "mean_top_pick_probability": 0.3855,
      "mean_actual_winner_probability": 0.3176,
      "mean_winner_brier_score": 0.6444,
      "mean_actual_log_loss": 1.2158,
      "weighted_top_pick_calibration_gap": 0.2394,
      "market_scored_events": 1,
      "paper_trade_candidate_events": 1,
      "paper_trade_candidate_hit_rate": 0.0
    },
    "warnings": [
      "diagnostic_only_not_formal_probability_calibration",
      "same_replay_inputs_as_current_diagnostic_pipeline",
      "small_sample_less_than_20_scored_events",
      "market_scored_subset_incomplete"
    ]
  },
  "improvement_summary": {
    "status": "inputs_required",
    "formal_edge_ready": false,
    "top_priority": "Backfill Same-Time Market Snapshots",
    "blocking_workstream_count": 3,
    "diagnostic_workstream_count": 2,
    "workstreams": [
      {
        "workstream_id": "market_same_time_snapshots",
        "title": "Backfill Same-Time Market Snapshots",
        "priority": 1,
        "status": "blocked_no_usable_market_definitions",
        "blocks_formal_claim": true
      },
      {
        "workstream_id": "source_archive_proof",
        "title": "Replace or Prove Retrospective Sources",
        "priority": 2,
        "status": "replacement_candidates_need_archive_or_content_review",
        "blocks_formal_claim": true
      },
      {
        "workstream_id": "formal_replay_freeze",
        "title": "Regenerate Formal Replay Freeze",
        "priority": 3,
        "status": "blocked_by_input_readiness",
        "blocks_formal_claim": true
      },
      {
        "workstream_id": "probability_calibration",
        "title": "Recalibrate Probabilities After Input Fixes",
        "priority": 4,
        "status": "diagnostic_waiting_for_inputs",
        "blocks_formal_claim": false
      },
      {
        "workstream_id": "model_iteration",
        "title": "Review Misses and Model Assumptions",
        "priority": 5,
        "status": "diagnostic_after_formal_inputs",
        "blocks_formal_claim": false
      }
    ]
  },
  "root_causes": [
    {
      "code": "market_data_gap",
      "severity": "critical",
      "count": 7,
      "affected_events": [
        "chinese_gp",
        "japanese_gp",
        "miami_gp",
        "canadian_gp",
        "monaco_gp",
        "barcelona_gp",
        "austrian_gp"
      ],
      "diagnosis": "The replay can score race outcomes, but it cannot validate market edge or CLV without same-time prices for model-supported markets across most completed races.",
      "evidence": "2/8 scored replay rows have cutoff-valid supported-market snapshots; 6 are missing cutoff-valid rows and 2 have after-cutoff rows excluded.",
      "improvement": "Archive live Polymarket order-book snapshots at each future cutoff, and import reviewed historical CLOB definitions plus price history for completed 2026 races; use winner markets for formal winner-edge claims and supported non-winner markets for diagnostic gaps.",
      "blocks_formal_claim": true
    },
    {
      "code": "source_time_integrity_gap",
      "severity": "high",
      "count": 3,
      "affected_events": [
        "miami_gp",
        "canadian_gp",
        "barcelona_gp"
      ],
      "diagnosis": "The Codex evidence layer is populated, but some evidence was snapshotted after the prediction cutoff without cutoff-valid archive proof.",
      "evidence": "3 replay rows still rely on retrospective source snapshots; 5 scored rows have archive-backed source proof.",
      "improvement": "Replace retrospective rows with pre-cutoff snapshots or verified Wayback captures, and keep source-audit gating mandatory before ingesting claims.",
      "blocks_formal_claim": true
    },
    {
      "code": "model_ranking_calibration_gap",
      "severity": "medium",
      "count": 3,
      "affected_events": [
        "australian_gp",
        "barcelona_gp",
        "austrian_gp"
      ],
      "diagnosis": "The strategy-aware race-time simulator often keeps the true winner in contention, but its top-pick calibration is not strong enough for an edge claim.",
      "evidence": "Diagnostic top-pick hit rate is 0.625; median actual-winner rank is 1; 6/8 actual winners were ranked in the top 3.",
      "improvement": "Add stronger qualifying/practice/session features, calibrate the tyre/weather/strategy parameters against historical races, and track probability calibration before comparing against markets.",
      "blocks_formal_claim": false
    },
    {
      "code": "seed_label_provenance_gap",
      "severity": "low",
      "count": 3,
      "affected_events": [
        "australian_gp",
        "chinese_gp",
        "japanese_gp"
      ],
      "diagnosis": "Some seed scenario labels differ from canonical FastF1 results, but replay already uses FastF1 as the actual-result authority.",
      "evidence": "3 seed rows required canonical FastF1 result override.",
      "improvement": "Keep seed labels scenario-only, refresh seed fixtures from canonical result snapshots, and preserve the override warning as provenance.",
      "blocks_formal_claim": false
    }
  ],
  "timeline": [
    {
      "round_number": 1,
      "racing_sequence_number": 1,
      "event_id": "australian_gp",
      "event_name": "Australian Grand Prix",
      "date_end": "2026-03-08T06:00:00+00:00",
      "status": "replayed",
      "prediction_input_source": "seed",
      "event_input_quality": "seed_with_fastf1_result",
      "top_pick": "antonelli",
      "actual_winner": "russell",
      "hit": false,
      "actual_winner_probability": 0.1808,
      "actual_winner_rank": 4,
      "mean_abs_rank_error": 5.1818,
      "mean_abs_points_error": 2.6314,
      "podium_overlap_rate": 0.3333,
      "points_overlap_rate": 0.6,
      "evidence_count": 1,
      "evidence_quality_count": 1,
      "weak_evidence_quality_count": 0,
      "source_snapshot_count": 1,
      "retrospective_source_snapshot_count": 0,
      "market_snapshot_count": 1,
      "market_snapshot_after_cutoff_count": 0,
      "issue_codes": [
        "top_pick_miss",
        "seed_result_overridden_by_fastf1"
      ],
      "blocking_action_categories": [],
      "warning_action_categories": [
        "model_calibration_review"
      ]
    },
    {
      "round_number": 2,
      "racing_sequence_number": 2,
      "event_id": "chinese_gp",
      "event_name": "Chinese Grand Prix",
      "date_end": "2026-03-15T09:00:00+00:00",
      "status": "replayed",
      "prediction_input_source": "seed",
      "event_input_quality": "seed_with_fastf1_result",
      "top_pick": "antonelli",
      "actual_winner": "antonelli",
      "hit": true,
      "actual_winner_probability": 0.4025,
      "actual_winner_rank": 1,
      "mean_abs_rank_error": 6.2727,
      "mean_abs_points_error": 3.2815,
      "podium_overlap_rate": 0.6667,
      "points_overlap_rate": 0.5,
      "evidence_count": 1,
      "evidence_quality_count": 1,
      "weak_evidence_quality_count": 0,
      "source_snapshot_count": 1,
      "retrospective_source_snapshot_count": 0,
      "market_snapshot_count": 11,
      "market_snapshot_after_cutoff_count": 1,
      "issue_codes": [
        "market_snapshot_after_cutoff",
        "seed_result_overridden_by_fastf1"
      ],
      "blocking_action_categories": [],
      "warning_action_categories": [
        "after_cutoff_market_replacement"
      ]
    },
    {
      "round_number": 3,
      "racing_sequence_number": 3,
      "event_id": "japanese_gp",
      "event_name": "Japanese Grand Prix",
      "date_end": "2026-03-29T07:00:00+00:00",
      "status": "replayed",
      "prediction_input_source": "seed",
      "event_input_quality": "seed_with_fastf1_result",
      "top_pick": "antonelli",
      "actual_winner": "antonelli",
      "hit": true,
      "actual_winner_probability": 0.3933,
      "actual_winner_rank": 1,
      "mean_abs_rank_error": 4.8182,
      "mean_abs_points_error": 2.7941,
      "podium_overlap_rate": 0.3333,
      "points_overlap_rate": 0.7,
      "evidence_count": 1,
      "evidence_quality_count": 1,
      "weak_evidence_quality_count": 0,
      "source_snapshot_count": 1,
      "retrospective_source_snapshot_count": 0,
      "market_snapshot_count": 0,
      "market_snapshot_after_cutoff_count": 1,
      "issue_codes": [
        "missing_market_snapshot",
        "market_snapshot_after_cutoff",
        "seed_result_overridden_by_fastf1"
      ],
      "blocking_action_categories": [
        "market_snapshot_required"
      ],
      "warning_action_categories": [
        "after_cutoff_market_replacement"
      ]
    },
    {
      "round_number": 4,
      "racing_sequence_number": null,
      "event_id": "Bahrain Grand Prix",
      "event_name": "Bahrain Grand Prix",
      "date_end": "2026-04-12T17:00:00+00:00",
      "status": "cancelled",
      "prediction_input_source": null,
      "event_input_quality": null,
      "top_pick": null,
      "actual_winner": null,
      "hit": null,
      "actual_winner_probability": null,
      "actual_winner_rank": null,
      "mean_abs_rank_error": null,
      "mean_abs_points_error": null,
      "podium_overlap_rate": null,
      "points_overlap_rate": null,
      "evidence_count": 0,
      "evidence_quality_count": 0,
      "weak_evidence_quality_count": 0,
      "source_snapshot_count": 0,
      "retrospective_source_snapshot_count": 0,
      "market_snapshot_count": 0,
      "market_snapshot_after_cutoff_count": 0,
      "issue_codes": [],
      "blocking_action_categories": [],
      "warning_action_categories": []
    },
    {
      "round_number": 5,
      "racing_sequence_number": null,
      "event_id": "Saudi Arabian Grand Prix",
      "event_name": "Saudi Arabian Grand Prix",
      "date_end": "2026-04-19T19:00:00+00:00",
      "status": "cancelled",
      "prediction_input_source": null,
      "event_input_quality": null,
      "top_pick": null,
      "actual_winner": null,
      "hit": null,
      "actual_winner_probability": null,
      "actual_winner_rank": null,
      "mean_abs_rank_error": null,
      "mean_abs_points_error": null,
      "podium_overlap_rate": null,
      "points_overlap_rate": null,
      "evidence_count": 0,
      "evidence_quality_count": 0,
      "weak_evidence_quality_count": 0,
      "source_snapshot_count": 0,
      "retrospective_source_snapshot_count": 0,
      "market_snapshot_count": 0,
      "market_snapshot_after_cutoff_count": 0,
      "issue_codes": [],
      "blocking_action_categories": [],
      "warning_action_categories": []
    },
    {
      "round_number": 6,
      "racing_sequence_number": 4,
      "event_id": "miami_gp",
      "event_name": "Miami Grand Prix",
      "date_end": "2026-05-03T19:00:00+00:00",
      "status": "replayed",
      "prediction_input_source": "openf1_calendar_generated",
      "event_input_quality": "generated_verified",
      "top_pick": "antonelli",
      "actual_winner": "antonelli",
      "hit": true,
      "actual_winner_probability": 0.2875,
      "actual_winner_rank": 1,
      "mean_abs_rank_error": 4.2727,
      "mean_abs_points_error": 2.8433,
      "podium_overlap_rate": 0.3333,
      "points_overlap_rate": 0.7,
      "evidence_count": 1,
      "evidence_quality_count": 1,
      "weak_evidence_quality_count": 1,
      "source_snapshot_count": 1,
      "retrospective_source_snapshot_count": 1,
      "market_snapshot_count": 0,
      "market_snapshot_after_cutoff_count": 0,
      "issue_codes": [
        "missing_market_snapshot",
        "retrospective_source_snapshots"
      ],
      "blocking_action_categories": [
        "market_snapshot_required",
        "source_archive_required"
      ],
      "warning_action_categories": []
    },
    {
      "round_number": 7,
      "racing_sequence_number": 5,
      "event_id": "canadian_gp",
      "event_name": "Canadian Grand Prix",
      "date_end": "2026-05-24T22:00:00+00:00",
      "status": "replayed",
      "prediction_input_source": "openf1_calendar_generated",
      "event_input_quality": "generated_verified",
      "top_pick": "antonelli",
      "actual_winner": "antonelli",
      "hit": true,
      "actual_winner_probability": 0.5017,
      "actual_winner_rank": 1,
      "mean_abs_rank_error": 5.5455,
      "mean_abs_points_error": 3.5605,
      "podium_overlap_rate": 0.6667,
      "points_overlap_rate": 0.5,
      "evidence_count": 1,
      "evidence_quality_count": 1,
      "weak_evidence_quality_count": 1,
      "source_snapshot_count": 1,
      "retrospective_source_snapshot_count": 1,
      "market_snapshot_count": 0,
      "market_snapshot_after_cutoff_count": 0,
      "issue_codes": [
        "missing_market_snapshot",
        "retrospective_source_snapshots"
      ],
      "blocking_action_categories": [
        "market_snapshot_required",
        "source_archive_required"
      ],
      "warning_action_categories": []
    },
    {
      "round_number": 8,
      "racing_sequence_number": 6,
      "event_id": "monaco_gp",
      "event_name": "Monaco Grand Prix",
      "date_end": "2026-06-07T15:00:00+00:00",
      "status": "replayed",
      "prediction_input_source": "openf1_calendar_generated",
      "event_input_quality": "generated_verified",
      "top_pick": "antonelli",
      "actual_winner": "antonelli",
      "hit": true,
      "actual_winner_probability": 0.3808,
      "actual_winner_rank": 1,
      "mean_abs_rank_error": 6.2727,
      "mean_abs_points_error": 4.7264,
      "podium_overlap_rate": 0.6667,
      "points_overlap_rate": 0.5,
      "evidence_count": 1,
      "evidence_quality_count": 1,
      "weak_evidence_quality_count": 0,
      "source_snapshot_count": 1,
      "retrospective_source_snapshot_count": 0,
      "market_snapshot_count": 0,
      "market_snapshot_after_cutoff_count": 0,
      "issue_codes": [
        "missing_market_snapshot"
      ],
      "blocking_action_categories": [
        "market_snapshot_required"
      ],
      "warning_action_categories": []
    },
    {
      "round_number": 9,
      "racing_sequence_number": 7,
      "event_id": "barcelona_gp",
      "event_name": "Barcelona Grand Prix",
      "date_end": "2026-06-14T15:00:00+00:00",
      "status": "replayed",
      "prediction_input_source": "openf1_calendar_generated",
      "event_input_quality": "generated_verified",
      "top_pick": "antonelli",
      "actual_winner": "hamilton",
      "hit": false,
      "actual_winner_probability": 0.1675,
      "actual_winner_rank": 4,
      "mean_abs_rank_error": 5.3636,
      "mean_abs_points_error": 3.2614,
      "podium_overlap_rate": 0.3333,
      "points_overlap_rate": 0.6,
      "evidence_count": 1,
      "evidence_quality_count": 1,
      "weak_evidence_quality_count": 1,
      "source_snapshot_count": 1,
      "retrospective_source_snapshot_count": 1,
      "market_snapshot_count": 0,
      "market_snapshot_after_cutoff_count": 0,
      "issue_codes": [
        "missing_market_snapshot",
        "retrospective_source_snapshots",
        "top_pick_miss"
      ],
      "blocking_action_categories": [
        "market_snapshot_required",
        "source_archive_required"
      ],
      "warning_action_categories": [
        "model_calibration_review"
      ]
    },
    {
      "round_number": 10,
      "racing_sequence_number": 8,
      "event_id": "austrian_gp",
      "event_name": "Austrian Grand Prix",
      "date_end": "2026-06-28T15:00:00+00:00",
      "status": "replayed",
      "prediction_input_source": "openf1_calendar_generated",
      "event_input_quality": "generated_verified",
      "top_pick": "antonelli",
      "actual_winner": "russell",
      "hit": false,
      "actual_winner_probability": 0.2267,
      "actual_winner_rank": 2,
      "mean_abs_rank_error": 3.8182,
      "mean_abs_points_error": 2.0017,
      "podium_overlap_rate": 1.0,
      "points_overlap_rate": 0.8,
      "evidence_count": 1,
      "evidence_quality_count": 1,
      "weak_evidence_quality_count": 0,
      "source_snapshot_count": 1,
      "retrospective_source_snapshot_count": 0,
      "market_snapshot_count": 0,
      "market_snapshot_after_cutoff_count": 0,
      "issue_codes": [
        "missing_market_snapshot",
        "top_pick_miss"
      ],
      "blocking_action_categories": [
        "market_snapshot_required"
      ],
      "warning_action_categories": [
        "model_calibration_review"
      ]
    },
    {
      "round_number": 11,
      "racing_sequence_number": 9,
      "event_id": "british_gp",
      "event_name": "British Grand Prix",
      "date_end": "2026-07-05T16:00:00+00:00",
      "status": "not_due",
      "prediction_input_source": "seed",
      "event_input_quality": "seed",
      "top_pick": null,
      "actual_winner": null,
      "hit": null,
      "actual_winner_probability": null,
      "actual_winner_rank": null,
      "mean_abs_rank_error": null,
      "mean_abs_points_error": null,
      "podium_overlap_rate": null,
      "points_overlap_rate": null,
      "evidence_count": 0,
      "evidence_quality_count": 0,
      "weak_evidence_quality_count": 0,
      "source_snapshot_count": 0,
      "retrospective_source_snapshot_count": 0,
      "market_snapshot_count": 0,
      "market_snapshot_after_cutoff_count": 0,
      "issue_codes": [],
      "blocking_action_categories": [],
      "warning_action_categories": []
    },
    {
      "round_number": 12,
      "racing_sequence_number": 10,
      "event_id": "belgian_gp",
      "event_name": "Belgian Grand Prix",
      "date_end": "2026-07-19T15:00:00+00:00",
      "status": "not_due",
      "prediction_input_source": "seed",
      "event_input_quality": "seed",
      "top_pick": null,
      "actual_winner": null,
      "hit": null,
      "actual_winner_probability": null,
      "actual_winner_rank": null,
      "mean_abs_rank_error": null,
      "mean_abs_points_error": null,
      "podium_overlap_rate": null,
      "points_overlap_rate": null,
      "evidence_count": 0,
      "evidence_quality_count": 0,
      "weak_evidence_quality_count": 0,
      "source_snapshot_count": 0,
      "retrospective_source_snapshot_count": 0,
      "market_snapshot_count": 0,
      "market_snapshot_after_cutoff_count": 0,
      "issue_codes": [],
      "blocking_action_categories": [],
      "warning_action_categories": []
    },
    {
      "round_number": 13,
      "racing_sequence_number": 11,
      "event_id": "hungarian_gp",
      "event_name": "Hungarian Grand Prix",
      "date_end": "2026-07-26T15:00:00+00:00",
      "status": "not_due",
      "prediction_input_source": "openf1_calendar_generated",
      "event_input_quality": "generated_verified",
      "top_pick": null,
      "actual_winner": null,
      "hit": null,
      "actual_winner_probability": null,
      "actual_winner_rank": null,
      "mean_abs_rank_error": null,
      "mean_abs_points_error": null,
      "podium_overlap_rate": null,
      "points_overlap_rate": null,
      "evidence_count": 0,
      "evidence_quality_count": 0,
      "weak_evidence_quality_count": 0,
      "source_snapshot_count": 0,
      "retrospective_source_snapshot_count": 0,
      "market_snapshot_count": 0,
      "market_snapshot_after_cutoff_count": 0,
      "issue_codes": [],
      "blocking_action_categories": [],
      "warning_action_categories": []
    },
    {
      "round_number": 14,
      "racing_sequence_number": 12,
      "event_id": "dutch_gp",
      "event_name": "Dutch Grand Prix",
      "date_end": "2026-08-23T15:00:00+00:00",
      "status": "not_due",
      "prediction_input_source": "openf1_calendar_generated",
      "event_input_quality": "generated_verified",
      "top_pick": null,
      "actual_winner": null,
      "hit": null,
      "actual_winner_probability": null,
      "actual_winner_rank": null,
      "mean_abs_rank_error": null,
      "mean_abs_points_error": null,
      "podium_overlap_rate": null,
      "points_overlap_rate": null,
      "evidence_count": 0,
      "evidence_quality_count": 0,
      "weak_evidence_quality_count": 0,
      "source_snapshot_count": 0,
      "retrospective_source_snapshot_count": 0,
      "market_snapshot_count": 0,
      "market_snapshot_after_cutoff_count": 0,
      "issue_codes": [],
      "blocking_action_categories": [],
      "warning_action_categories": []
    },
    {
      "round_number": 15,
      "racing_sequence_number": 13,
      "event_id": "italian_gp",
      "event_name": "Italian Grand Prix",
      "date_end": "2026-09-06T15:00:00+00:00",
      "status": "not_due",
      "prediction_input_source": "openf1_calendar_generated",
      "event_input_quality": "generated_verified",
      "top_pick": null,
      "actual_winner": null,
      "hit": null,
      "actual_winner_probability": null,
      "actual_winner_rank": null,
      "mean_abs_rank_error": null,
      "mean_abs_points_error": null,
      "podium_overlap_rate": null,
      "points_overlap_rate": null,
      "evidence_count": 0,
      "evidence_quality_count": 0,
      "weak_evidence_quality_count": 0,
      "source_snapshot_count": 0,
      "retrospective_source_snapshot_count": 0,
      "market_snapshot_count": 0,
      "market_snapshot_after_cutoff_count": 0,
      "issue_codes": [],
      "blocking_action_categories": [],
      "warning_action_categories": []
    },
    {
      "round_number": 16,
      "racing_sequence_number": 14,
      "event_id": "spanish_gp",
      "event_name": "Spanish Grand Prix",
      "date_end": "2026-09-13T15:00:00+00:00",
      "status": "not_due",
      "prediction_input_source": "openf1_calendar_generated",
      "event_input_quality": "generated_verified",
      "top_pick": null,
      "actual_winner": null,
      "hit": null,
      "actual_winner_probability": null,
      "actual_winner_rank": null,
      "mean_abs_rank_error": null,
      "mean_abs_points_error": null,
      "podium_overlap_rate": null,
      "points_overlap_rate": null,
      "evidence_count": 0,
      "evidence_quality_count": 0,
      "weak_evidence_quality_count": 0,
      "source_snapshot_count": 0,
      "retrospective_source_snapshot_count": 0,
      "market_snapshot_count": 0,
      "market_snapshot_after_cutoff_count": 0,
      "issue_codes": [],
      "blocking_action_categories": [],
      "warning_action_categories": []
    },
    {
      "round_number": 17,
      "racing_sequence_number": 15,
      "event_id": "azerbaijan_gp",
      "event_name": "Azerbaijan Grand Prix",
      "date_end": "2026-09-26T13:00:00+00:00",
      "status": "not_due",
      "prediction_input_source": "openf1_calendar_generated",
      "event_input_quality": "generated_verified",
      "top_pick": null,
      "actual_winner": null,
      "hit": null,
      "actual_winner_probability": null,
      "actual_winner_rank": null,
      "mean_abs_rank_error": null,
      "mean_abs_points_error": null,
      "podium_overlap_rate": null,
      "points_overlap_rate": null,
      "evidence_count": 0,
      "evidence_quality_count": 0,
      "weak_evidence_quality_count": 0,
      "source_snapshot_count": 0,
      "retrospective_source_snapshot_count": 0,
      "market_snapshot_count": 0,
      "market_snapshot_after_cutoff_count": 0,
      "issue_codes": [],
      "blocking_action_categories": [],
      "warning_action_categories": []
    },
    {
      "round_number": 18,
      "racing_sequence_number": 16,
      "event_id": "singapore_gp",
      "event_name": "Singapore Grand Prix",
      "date_end": "2026-10-11T14:00:00+00:00",
      "status": "not_due",
      "prediction_input_source": "openf1_calendar_generated",
      "event_input_quality": "generated_verified",
      "top_pick": null,
      "actual_winner": null,
      "hit": null,
      "actual_winner_probability": null,
      "actual_winner_rank": null,
      "mean_abs_rank_error": null,
      "mean_abs_points_error": null,
      "podium_overlap_rate": null,
      "points_overlap_rate": null,
      "evidence_count": 0,
      "evidence_quality_count": 0,
      "weak_evidence_quality_count": 0,
      "source_snapshot_count": 0,
      "retrospective_source_snapshot_count": 0,
      "market_snapshot_count": 0,
      "market_snapshot_after_cutoff_count": 0,
      "issue_codes": [],
      "blocking_action_categories": [],
      "warning_action_categories": []
    },
    {
      "round_number": 19,
      "racing_sequence_number": 17,
      "event_id": "united_states_gp",
      "event_name": "United States Grand Prix",
      "date_end": "2026-10-25T22:00:00+00:00",
      "status": "not_due",
      "prediction_input_source": "openf1_calendar_generated",
      "event_input_quality": "generated_verified",
      "top_pick": null,
      "actual_winner": null,
      "hit": null,
      "actual_winner_probability": null,
      "actual_winner_rank": null,
      "mean_abs_rank_error": null,
      "mean_abs_points_error": null,
      "podium_overlap_rate": null,
      "points_overlap_rate": null,
      "evidence_count": 0,
      "evidence_quality_count": 0,
      "weak_evidence_quality_count": 0,
      "source_snapshot_count": 0,
      "retrospective_source_snapshot_count": 0,
      "market_snapshot_count": 0,
      "market_snapshot_after_cutoff_count": 0,
      "issue_codes": [],
      "blocking_action_categories": [],
      "warning_action_categories": []
    },
    {
      "round_number": 20,
      "racing_sequence_number": 18,
      "event_id": "mexico_city_gp",
      "event_name": "Mexico City Grand Prix",
      "date_end": "2026-11-01T22:00:00+00:00",
      "status": "not_due",
      "prediction_input_source": "openf1_calendar_generated",
      "event_input_quality": "generated_verified",
      "top_pick": null,
      "actual_winner": null,
      "hit": null,
      "actual_winner_probability": null,
      "actual_winner_rank": null,
      "mean_abs_rank_error": null,
      "mean_abs_points_error": null,
      "podium_overlap_rate": null,
      "points_overlap_rate": null,
      "evidence_count": 0,
      "evidence_quality_count": 0,
      "weak_evidence_quality_count": 0,
      "source_snapshot_count": 0,
      "retrospective_source_snapshot_count": 0,
      "market_snapshot_count": 0,
      "market_snapshot_after_cutoff_count": 0,
      "issue_codes": [],
      "blocking_action_categories": [],
      "warning_action_categories": []
    },
    {
      "round_number": 21,
      "racing_sequence_number": 19,
      "event_id": "sao_paulo_gp",
      "event_name": "São Paulo Grand Prix",
      "date_end": "2026-11-08T19:00:00+00:00",
      "status": "not_due",
      "prediction_input_source": "openf1_calendar_generated",
      "event_input_quality": "generated_verified",
      "top_pick": null,
      "actual_winner": null,
      "hit": null,
      "actual_winner_probability": null,
      "actual_winner_rank": null,
      "mean_abs_rank_error": null,
      "mean_abs_points_error": null,
      "podium_overlap_rate": null,
      "points_overlap_rate": null,
      "evidence_count": 0,
      "evidence_quality_count": 0,
      "weak_evidence_quality_count": 0,
      "source_snapshot_count": 0,
      "retrospective_source_snapshot_count": 0,
      "market_snapshot_count": 0,
      "market_snapshot_after_cutoff_count": 0,
      "issue_codes": [],
      "blocking_action_categories": [],
      "warning_action_categories": []
    },
    {
      "round_number": 22,
      "racing_sequence_number": 20,
      "event_id": "las_vegas_gp",
      "event_name": "Las Vegas Grand Prix",
      "date_end": "2026-11-22T06:00:00+00:00",
      "status": "not_due",
      "prediction_input_source": "openf1_calendar_generated",
      "event_input_quality": "generated_verified",
      "top_pick": null,
      "actual_winner": null,
      "hit": null,
      "actual_winner_probability": null,
      "actual_winner_rank": null,
      "mean_abs_rank_error": null,
      "mean_abs_points_error": null,
      "podium_overlap_rate": null,
      "points_overlap_rate": null,
      "evidence_count": 0,
      "evidence_quality_count": 0,
      "weak_evidence_quality_count": 0,
      "source_snapshot_count": 0,
      "retrospective_source_snapshot_count": 0,
      "market_snapshot_count": 0,
      "market_snapshot_after_cutoff_count": 0,
      "issue_codes": [],
      "blocking_action_categories": [],
      "warning_action_categories": []
    },
    {
      "round_number": 23,
      "racing_sequence_number": 21,
      "event_id": "qatar_gp",
      "event_name": "Qatar Grand Prix",
      "date_end": "2026-11-29T18:00:00+00:00",
      "status": "not_due",
      "prediction_input_source": "openf1_calendar_generated",
      "event_input_quality": "generated_verified",
      "top_pick": null,
      "actual_winner": null,
      "hit": null,
      "actual_winner_probability": null,
      "actual_winner_rank": null,
      "mean_abs_rank_error": null,
      "mean_abs_points_error": null,
      "podium_overlap_rate": null,
      "points_overlap_rate": null,
      "evidence_count": 0,
      "evidence_quality_count": 0,
      "weak_evidence_quality_count": 0,
      "source_snapshot_count": 0,
      "retrospective_source_snapshot_count": 0,
      "market_snapshot_count": 0,
      "market_snapshot_after_cutoff_count": 0,
      "issue_codes": [],
      "blocking_action_categories": [],
      "warning_action_categories": []
    },
    {
      "round_number": 24,
      "racing_sequence_number": 22,
      "event_id": "abu_dhabi_gp",
      "event_name": "Abu Dhabi Grand Prix",
      "date_end": "2026-12-06T15:00:00+00:00",
      "status": "not_due",
      "prediction_input_source": "openf1_calendar_generated",
      "event_input_quality": "generated_verified",
      "top_pick": null,
      "actual_winner": null,
      "hit": null,
      "actual_winner_probability": null,
      "actual_winner_rank": null,
      "mean_abs_rank_error": null,
      "mean_abs_points_error": null,
      "podium_overlap_rate": null,
      "points_overlap_rate": null,
      "evidence_count": 0,
      "evidence_quality_count": 0,
      "weak_evidence_quality_count": 0,
      "source_snapshot_count": 0,
      "retrospective_source_snapshot_count": 0,
      "market_snapshot_count": 0,
      "market_snapshot_after_cutoff_count": 0,
      "issue_codes": [],
      "blocking_action_categories": [],
      "warning_action_categories": []
    }
  ],
  "next_actions": [
    "P1 Backfill Same-Time Market Snapshots: blocked_no_usable_market_definitions",
    "P2 Replace or Prove Retrospective Sources: replacement_candidates_need_archive_or_content_review",
    "P3 Regenerate Formal Replay Freeze: blocked_by_input_readiness"
  ],
  "artifact_refs": {
    "chronological_replay_json": "reports\\chronological_replay_v2_team_strength_reestimate\\2026_asof_20260701T000000_0000.chronological_replay.json",
    "chronological_replay_markdown": "reports\\chronological_replay_v2_team_strength_reestimate\\2026_asof_20260701T000000_0000.chronological_replay.md"
  },
  "warnings": [
    "diagnostic_replay_not_formal_backtest",
    "formal_readiness_inputs_required",
    "probability_calibration_diagnostic_only",
    "diagnostic_only_not_formal_probability_calibration",
    "same_replay_inputs_as_current_diagnostic_pipeline",
    "small_sample_less_than_20_scored_events",
    "market_scored_subset_incomplete"
  ]
}